Metadata-Version: 1.1
Name: lts
Version: 0.0.2
Summary: A basic list to string converter
Home-page: UNKNOWN
Author: Peter Kyle
Author-email: peterdooga@gmail.com
License: MIT
Keywords: lts
Platform: UNKNOWN
Classifier: Development Status :: 5 - Production/Stable
Classifier: Intended Audience :: Education
Classifier: Operating System :: Microsoft :: Windows :: Windows 10
Classifier: License :: OSI Approved :: MIT License
Classifier: Programming Language :: Python :: 3
